FrozenPy/FrozenPy.py
FrozenPy/__init__.py
FrozenPy/functions.py
FrozenPy-0.3.3.dist-info/LICENSE.md
FrozenPy-0.3.3.dist-info/METADATA
FrozenPy-0.3.3.dist-info/WHEEL
FrozenPy-0.3.3.dist-info/top_level.txt
FrozenPy-0.3.3.dist-info/RECORD
