Metadata-Version: 2.1
Name: FrozenPy
Version: 0.3.3
Summary: A small suit of function for analyzing freezing behavior based on a threshold.
Home-page: https://github.com/MicTott/FrozenPy
Author: Michael Totty
Author-email: MicTott@gmail.com
License: MIT License
Platform: UNKNOWN
Requires-Dist: numpy
Requires-Dist: pandas
